uuid_gen.py
mseep_mcp_uuid_gen-0.1.1.dist-info/METADATA
mseep_mcp_uuid_gen-0.1.1.dist-info/WHEEL
mseep_mcp_uuid_gen-0.1.1.dist-info/top_level.txt
mseep_mcp_uuid_gen-0.1.1.dist-info/RECORD
