Metadata-Version: 2.4
Name: mseep-mcp-uuid-gen
Version: 0.1.1
Summary: Add your description here
Author-email: mseep <support@skydeck.ai>
Requires-Python: >=3.13
Requires-Dist: mcp[cli]>=1.9.4
